OutlierIdentifiers/OutlierIdentifiers.py
OutlierIdentifiers/__init__.py
OutlierIdentifiers-0.1.2.dist-info/LICENSE
OutlierIdentifiers-0.1.2.dist-info/METADATA
OutlierIdentifiers-0.1.2.dist-info/WHEEL
OutlierIdentifiers-0.1.2.dist-info/top_level.txt
OutlierIdentifiers-0.1.2.dist-info/RECORD
