Metadata-Version: 2.1
Name: OutlierIdentifiers
Version: 0.1.2
Summary: Outlier identifiers functions package.
Home-page: https://github.com/antononcube/Python-packages/tree/main/OutlierIdentifiers
Author: Anton Antonov
Author-email: antononcube@posteo.net
Keywords: outlier identifiers,outlier detection,outlier,outliers,detection,ml,machine learning
Classifier: Intended Audience :: Science/Research
Classifier: Intended Audience :: Developers
Classifier: Programming Language :: Python :: 3
Classifier: License :: OSI Approved :: BSD License
Classifier: Intended Audience :: Science/Research
Classifier: Intended Audience :: Developers
Classifier: Operating System :: OS Independent
Requires-Python: >=3.7
License-File: LICENSE
Requires-Dist: numpy
